becalib/__init__.py
becalib/air_resistances.py
becalib/algos.py
becalib/charts.py
becalib/component.py
becalib/layers.py
becalib/translator.py
becalib/locales/en/LC_MESSAGES/becalib.mo
becalib/locales/en/LC_MESSAGES/becalib.po
becalib/locales/en/LC_MESSAGES/becalib.po~
becalib/locales/fr/LC_MESSAGES/becalib.mo
becalib/locales/fr/LC_MESSAGES/becalib.po
becalib/locales/fr/LC_MESSAGES/becalib.po~
becalib-0.0.1.dist-info/METADATA
becalib-0.0.1.dist-info/WHEEL
becalib-0.0.1.dist-info/licenses/LICENSE
becalib-0.0.1.dist-info/RECORD
