Metadata-Version: 2.3
Name: becalib
Version: 0.0.1
Summary: Building Envelope Components Analysis Library 
Project-URL: Repository, https://github.com/SimoneAragno/becalib
Project-URL: Changelog, https://github.com/SimoneAragno/becalib/blob/main/CHANGELOG.md
Author-email: Simone ARAGNO <aragno.simone@gmail.com>
Maintainer-email: Simone ARAGNO <aragno.simone@gmail.com>
License: MIT License
License-File: LICENSE
Keywords: Areal heat capacity,Building,Building physics,Decrement factor,Envelope,Facade,ISO 13786,Summer performance,Time shift,Wall
Classifier: Development Status :: 4 - Beta
Classifier: License :: OSI Approved :: MIT License
Classifier: Operating System :: OS Independent
Classifier: Programming Language :: Python :: 3
Requires-Python: >=3.10
